[{ "deviceId" : "ATPL-909154-AIPTZ", "productType": "S-Series"},
{ "deviceId" : "ATPL-910419-AIPTZ", "productType": "S-Series"},
{ "deviceId" : "ATPL-907971-AIPTZ", "productType": "S-Series"},
{ "deviceId" : "ATPL-910178-AIPTZ", "productType": "S-Series"},
{ "deviceId" : "ATPL-909123-AIPTZ", "productType": "S-Series"},
{ "deviceId" : "ATPL-908694-AIPTZ", "productType": "S-Series"},
{ "deviceId" : "ATPL-909650-AIPTZ", "productType": "S-Series"},
{ "deviceId" : "ATPL-910172-AIPTZ", "productType": "S-Series"},
{ "deviceId" : "ATPL-909081-AIPTZ", "productType": "S-Series"},
{ "deviceId" : "ATPL-907367-AIPTZ", "productType": "S-Series"},
{ "deviceId" : "ATPL-910162-AIPTZ", "productType": "S-Series"},
{ "deviceId" : "ATPL-908604-AIPTZ", "productType": "S-Series"},
{ "deviceId" : "ATPL-910397-AIPTZ", "productType": "S-Series"},
{ "deviceId" : "ATPL-909397-AIPTZ", "productType": "S-Series"},
{ "deviceId" : "ATPL-907983-AIPTZ", "productType": "S-Series"},
{ "deviceId" : "ATPL-909161-AIPTZ", "productType": "S-Series"},
{ "deviceId" : "ATPL-909332-AIPTZ", "productType": "S-Series"},
{ "deviceId" : "ATPL-908248-AIPTZ", "productType": "S-Series"},
{ "deviceId" : "ATPL-907975-AIPTZ", "productType": "S-Series"},
{ "deviceId" : "ATPL-908463-AIPTZ", "productType": "S-Series"},
{ "deviceId" : "ATPL-908612-AIPTZ", "productType": "S-Series"}]